kamilu/__init__.py
kamilu/main.py
kamilu-0.0.6.dist-info/entry_points.txt
kamilu-0.0.6.dist-info/LICENSE
kamilu-0.0.6.dist-info/WHEEL
kamilu-0.0.6.dist-info/METADATA
kamilu-0.0.6.dist-info/RECORD
